setup.cfg
setup.py
NIM_API_Python.egg-info/PKG-INFO
NIM_API_Python.egg-info/SOURCES.txt
NIM_API_Python.egg-info/dependency_links.txt
NIM_API_Python.egg-info/not-zip-safe
NIM_API_Python.egg-info/requires.txt
NIM_API_Python.egg-info/top_level.txt
netease_im/__init__.py
netease_im/client.py
netease_im/util.py
netease_im/components/__init__.py
netease_im/components/base.py
netease_im/components/chatroom.py
netease_im/components/event.py
netease_im/components/friend.py
netease_im/components/history.py
netease_im/components/message.py
netease_im/components/team.py
netease_im/components/user.py
netease_im/constants/__init__.py
netease_im/constants/code.py
netease_im/constants/params.py